helloworld.py
helloworld_fake_test-0.0.1.dist-info/LICENSE.txt
helloworld_fake_test-0.0.1.dist-info/METADATA
helloworld_fake_test-0.0.1.dist-info/WHEEL
helloworld_fake_test-0.0.1.dist-info/top_level.txt
helloworld_fake_test-0.0.1.dist-info/RECORD
